{"assets":{"3B030C012EC56C307089626AD7E9F96C":{"type":"texture","index":36,"assetRequest":{"type":"slide","state":"outgoing","slide":"DB86DEC4-D85E-4F96-927D-D2133CB92497"},"url":"assets/3B030C012EC56C307089626AD7E9F96C.svg","width":1920,"height":1080},"6F84EF7FA221426EE4136AECA3FC4E20":{"type":"texture","index":37,"assetRequest":{"type":"slide","state":"incoming","slide":"485D204B-41B8-4E78-96DC-6C7363FFE84C"},"url":"assets/6F84EF7FA221426EE4136AECA3FC4E20.svg","width":1920,"height":1080}},"events":[{"effects":[{"beginTime":0,"baseLayer":{"animations":[],"initialState":{"affineTransform":[1,0,0,1,0,0],"masksToBounds":true,"rotation":0,"scale":1,"position":{"pointX":960,"pointY":540},"width":1920,"sublayerTransform":[1,0,0,0,0,1,0,0,0,0,1,0,0,0,0,1],"contentsRect":{"y":0,"x":0,"width":1,"height":1},"opacity":1,"edgeAntialiasingMask":0,"height":1080,"hidden":false,"anchorPoint":{"pointX":0.5,"pointY":0.5}},"objectID":"0","layers":[{"animations":[],"initialState":{"affineTransform":[1,0,0,1,0,0],"masksToBounds":false,"rotation":0,"scale":1,"position":{"pointX":960,"pointY":540},"width":1920,"sublayerTransform":[1,0,0,0,0,1,0,0,0,0,1,-0.0003500791246677598,0,0,0,1],"contentsRect":{"y":0,"x":0,"width":1,"height":1},"opacity":1,"edgeAntialiasingMask":15,"height":1080,"hidden":false,"anchorPoint":{"pointX":0.5,"pointY":0.5}},"layers":[{"animations":[],"layers":[],"initialState":{"affineTransform":[1,0,0,1,0,0],"masksToBounds":false,"rotation":0,"scale":1,"position":{"pointX":960,"pointY":540},"width":1920,"sublayerTransform":[1,0,0,0,0,1,0,0,0,0,1,0,0,0,0,1],"contentsRect":{"y":0,"x":0,"width":1,"height":1},"opacity":1,"edgeAntialiasingMask":0,"height":1080,"hidden":false,"anchorPoint":{"pointX":0.5,"pointY":0.5}},"texture":"6F84EF7FA221426EE4136AECA3FC4E20"},{"animations":[{"from":{"scalar":false},"beginTime":0,"repeatCount":0,"fillMode":"both","property":"hidden","duration":0.01,"to":{"scalar":true}}],"layers":[],"initialState":{"affineTransform":[1,0,0,1,0,0],"masksToBounds":false,"rotation":0,"scale":1,"position":{"pointX":960,"pointY":540},"width":1920,"sublayerTransform":[1,0,0,0,0,1,0,0,0,0,1,0,0,0,0,1],"contentsRect":{"y":0,"x":0,"width":1,"height":1},"opacity":1,"edgeAntialiasingMask":0,"height":1080,"hidden":false,"anchorPoint":{"pointX":0.5,"pointY":0.5}},"texture":"3B030C012EC56C307089626AD7E9F96C"}]}]},"effects":[],"duration":0.01,"type":"transition","name":"none","objectID":"0"}],"automaticPlay":false,"hyperlinks":[{"url":"http://bit.ly/1I3BjrZ","targetRectangle":{"y":251.8169052600861,"x":1268.739491939545,"width":307.22412109375,"height":42}},{"url":"http://linkd.in/1csNvqK","targetRectangle":{"y":903.1715034246445,"x":1063.618527650833,"width":148.3447265625,"height":30.1494140625}},{"url":"http://bit.ly/1I3BjrZ","targetRectangle":{"y":-11.531005859375,"x":-1106.755126953125,"width":2001.15625,"height":1103.0625}},{"url":"https://www.linkedin.com/in/wolfemichael","targetRectangle":{"y":1140.620285749435,"x":562.4969310760498,"width":163.5600000000001,"height":35.12979125976562}}],"accessibility":[{"text":"pasted-image.pdf","targetRectangle":{"y":51.84724426269531,"x":835.6666564941406,"width":120,"height":95.20294189453125}},{"text":"Co-founder @SaganSystems & serial entrepreneur","targetRectangle":{"y":903.1715031266212,"x":1230.501616477966,"width":588.580078125,"height":30.1494140625}},{"text":"   ","targetRectangle":{"y":532.1171798706055,"x":982.8671875,"width":26.6880000000001,"height":38}},{"text":"http://bit.ly/1I3BjrZ","targetRectangle":{"y":251.8169052600861,"x":1268.739491939545,"width":307.22412109375,"height":42}},{"text":"I needed to build something that would allow me to register participants, show inspiring imagery, use branching logic, collect payments and look good whilst doing it. It felt a lot more like I was building an app than a form. The people who are coming on the trip, think that I built an entire website to organize this trip!”","targetRectangle":{"y":441.2444706617625,"x":1046.7290625,"width":759.94875,"height":380.5110593333302}},{"text":"Ui/Ux","targetRectangle":{"y":92.26782160997391,"x":867.3526879549026,"width":56.62800000000004,"height":26.36184692382812}},{"text":"Michael Wolfe’s camping trip","targetRectangle":{"y":150.5064744949341,"x":1098.675596164107,"width":647.3519975216389,"height":64.43362426757812}},{"text":"Michael Wolf,","targetRectangle":{"y":903.1715034246445,"x":1063.618527650833,"width":155.568359375,"height":30.1494140625}},{"text":"13","targetRectangle":{"y":15.93510407209396,"x":12.32000058889389,"width":33.36,"height":36.12979125976562}},{"text":"“","targetRectangle":{"y":367.7978253364563,"x":1407.189758300781,"width":43.80712890625,"height":109.0857465221779}},{"text":"pasted-image.pdf","targetRectangle":{"y":136.0574798583984,"x":835.6666564941406,"width":120,"height":95.20294189453125}},{"text":"Logic","targetRectangle":{"y":263.478057205677,"x":867.5396856069565,"width":56.25400000000002,"height":26.36184692382812}},{"text":"Stripe","targetRectangle":{"y":177.478057205677,"x":865.5156877040863,"width":60.30200000000002,"height":26.36184692382812}},{"text":"pasted-image.png","targetRectangle":{"y":-11.531005859375,"x":-1106.755126953125,"width":2001.15625,"height":1103.0625}},{"text":"pasted-image.pdf","targetRectangle":{"y":222.0574798583984,"x":835.6666564941406,"width":120,"height":95.20294189453125}},{"text":"Michael Wolf, Co-founder @SaganSystems & serial entrepreneur","targetRectangle":{"y":1140.620285749435,"x":562.4969310760498,"width":827.7600000000004,"height":35.12979125976562}},{"text":"noun_12540.png","targetRectangle":{"y":43.24868011474609,"x":1386.151517868042,"width":72.40007019042969,"height":72.40007019042969}},{"text":"pasted-image.pdf","targetRectangle":{"y":1330.01229429245,"x":742.2505187988281,"width":212.1286315917969,"height":56.22601699829102}}],"baseLayer":{"animations":[],"initialState":{"affineTransform":[1,0,0,1,0,0],"masksToBounds":true,"rotation":0,"scale":1,"position":{"pointX":960,"pointY":540},"width":1920,"sublayerTransform":[1,0,0,0,0,1,0,0,0,0,1,0,0,0,0,1],"contentsRect":{"y":0,"x":0,"width":1,"height":1},"opacity":1,"edgeAntialiasingMask":0,"height":1080,"hidden":false,"anchorPoint":{"pointX":0.5,"pointY":0.5}},"objectID":"0","layers":[{"animations":[],"initialState":{"affineTransform":[1,0,0,1,0,0],"masksToBounds":false,"rotation":0,"scale":1,"position":{"pointX":960,"pointY":540},"width":1920,"sublayerTransform":[1,0,0,0,0,1,0,0,0,0,1,-0.0003500791246677598,0,0,0,1],"contentsRect":{"y":0,"x":0,"width":1,"height":1},"opacity":1,"edgeAntialiasingMask":15,"height":1080,"hidden":false,"anchorPoint":{"pointX":0.5,"pointY":0.5}},"layers":[{"animations":[],"layers":[],"initialState":{"affineTransform":[1,0,0,1,0,0],"masksToBounds":false,"rotation":0,"scale":1,"position":{"pointX":960,"pointY":540},"width":1920,"sublayerTransform":[1,0,0,0,0,1,0,0,0,0,1,0,0,0,0,1],"contentsRect":{"y":0,"x":0,"width":1,"height":1},"opacity":1,"edgeAntialiasingMask":0,"height":1080,"hidden":false,"anchorPoint":{"pointX":0.5,"pointY":0.5}},"texture":"3B030C012EC56C307089626AD7E9F96C"}]}]}}]}